src_iverilog/is_zero.v
module is_zero (num, is_zero_out);
    parameter DATA_WIDTH = 16;
    parameter EXP_WIDTH = 8;
    parameter FRAC_WIDTH = 7;

    input [DATA_WIDTH-1:0] num;
    output is_zero_out;

    wire [EXP_WIDTH-1:0] exp;
    wire [FRAC_WIDTH-1:0] frac;

    assign exp = num[DATA_WIDTH-2:DATA_WIDTH-1-EXP_WIDTH];
    assign frac = num[FRAC_WIDTH-1:0];

    assign is_zero_out = ~((|exp) | (|frac));
endmodule

src_iverilog/is_inf.v
module is_inf (num, is_inf_out);
    parameter DATA_WIDTH = 16;
    parameter EXP_WIDTH = 8;
    parameter FRAC_WIDTH = 7;

    input [DATA_WIDTH-1:0] num;
    output is_inf_out;

    wire [EXP_WIDTH-1:0] exp;
    wire [FRAC_WIDTH-1:0] frac;

    assign exp = num[DATA_WIDTH-2:DATA_WIDTH-1-EXP_WIDTH];
    assign frac = num[FRAC_WIDTH-1:0];

    assign is_inf_out = (&exp) & ~(|frac);
endmodule

src_iverilog/is_NaN.v
module is_NaN (num, is_NaN_out);
    parameter DATA_WIDTH = 16;
    parameter EXP_WIDTH = 8;
    parameter FRAC_WIDTH = 7;

    input [DATA_WIDTH-1:0] num;
    output is_NaN_out;

    wire [EXP_WIDTH-1:0] exp;
    wire [FRAC_WIDTH-1:0] frac;

    assign exp = num[DATA_WIDTH-2:DATA_WIDTH-1-EXP_WIDTH];
    assign frac = num[FRAC_WIDTH-1:0];

    assign is_NaN_out = (&exp) & (|frac);
endmodule

src_iverilog/iv_fp_mul.v

module iv_fp_mul(
    input [DATA_WIDTH-1:0] in1,
    input [DATA_WIDTH-1:0] in2,
    output [DATA_WIDTH-1:0] out,
    output [ERROR_WIDTH-1:0] error
);
    parameter DATA_WIDTH = 16;
    parameter EXP_WIDTH = 8;
    parameter FRAC_WIDTH = 7;
    parameter ERROR_WIDTH = 2;

    wire op1_sign, op2_sign, op3_sign;
    wire [EXP_WIDTH-1:0] op1_exp, op2_exp, op3_exp;
    wire [FRAC_WIDTH-1:0] op1_frac, op2_frac, op3_frac;

    assign op1_sign = in1[DATA_WIDTH-1];
    assign op2_sign = in2[DATA_WIDTH-1];

    assign op1_exp = in1[DATA_WIDTH-2:DATA_WIDTH-1-EXP_WIDTH];
    assign op2_exp = in2[DATA_WIDTH-2:DATA_WIDTH-1-EXP_WIDTH];

    assign op1_frac = in1[FRAC_WIDTH-1:0];
    assign op2_frac = in2[FRAC_WIDTH-1:0];

    assign out = {op3_sign, op3_exp, op3_frac};

    // Input / Output Setup Complete

    // Fraction / Mantissa
    wire [(2*FRAC_WIDTH)+1:0] frac_prod;
    wire normalise;
    wire [FRAC_WIDTH-1:0] frac_prod_norm;
    assign frac_prod = {1'b1, op1_frac} * {1'b1, op2_frac};
    assign normalise = frac_prod[(2*FRAC_WIDTH)+1];
    assign frac_prod_norm = normalise ? frac_prod[(2*FRAC_WIDTH):FRAC_WIDTH+1] : frac_prod[(2*FRAC_WIDTH)-1:FRAC_WIDTH];
    
    // Exponent
    wire [EXP_WIDTH:0] exp_sum, exp_sum_plus_1, exp_sum_exp1_plus_exp2;
    wire [EXP_WIDTH-1:0] exp_sum_norm;
    assign exp_sum_exp1_plus_exp2 = {1'b0, op1_exp} + {1'b0, op2_exp};
    assign exp_sum = exp_sum_exp1_plus_exp2 - 9'd127; // 9 is exp_sum width
    assign exp_sum_plus_1 = exp_sum + 9'b1; // 9 is exp_sum width
    assign exp_sum_norm = normalise ? exp_sum_plus_1[EXP_WIDTH-1:0] : exp_sum[EXP_WIDTH-1:0];

    // -1 Exponent Case
    wire exp_underflow_border;
    wire [FRAC_WIDTH-1:0] frac_prod_underflow_border;
    assign exp_underflow_border = (&exp_sum_norm) | ~(|exp_sum_norm);
    assign frac_prod_underflow_border = frac_prod[(2*FRAC_WIDTH)+1:FRAC_WIDTH+2];

    // Error detection
    wire in1_is_NaN, in1_is_inf, in1_is_zero;
    wire in2_is_NaN, in2_is_inf, in2_is_zero;
    wire out_is_NaN, out_is_inf, out_is_zero;

    wire overflow, underflow, NaN, inf;
    assign overflow = exp_sum_exp1_plus_exp2[EXP_WIDTH] & (normalise ? exp_sum_plus_1[EXP_WIDTH] : exp_sum[EXP_WIDTH]);

    assign underflow = ~(exp_underflow_border) & ~(exp_sum_exp1_plus_exp2[EXP_WIDTH]) & (normalise ? exp_sum_plus_1[EXP_WIDTH] : exp_sum[EXP_WIDTH]);

    is_NaN is_NaN_1(.num(in1), .is_NaN_out(in1_is_NaN));
    is_inf is_inf_1(.num(in1), .is_inf_out(in1_is_inf));
    is_zero is_zero_1(.num(in1), .is_zero_out(in1_is_zero));

    is_NaN is_NaN_2(.num(in2), .is_NaN_out(in2_is_NaN));
    is_inf is_inf_2(.num(in2), .is_inf_out(in2_is_inf));
    is_zero is_zero_2(.num(in2), .is_zero_out(in2_is_zero));

    wire inf_x_0, NaN_input;
    assign inf_x_0 = ((in1_is_inf) & (in2_is_zero)) | ((in1_is_zero) & (in2_is_inf));
    assign NaN_input = (in1_is_NaN) | (in2_is_NaN);


    assign out_is_NaN = (NaN_input) | (inf_x_0);
    assign out_is_inf = ((in1_is_inf) & ~(in2_is_zero) & ~(in2_is_NaN)) | (~(in1_is_zero) & ~(in1_is_NaN) & (in2_is_inf)) | (overflow);
    assign out_is_zero = (~(in1_is_inf) & ~(in1_is_NaN) & (in2_is_zero)) | ((in1_is_zero) & ~(in2_is_NaN) & ~(in2_is_inf)) | (underflow);
    
    assign error = out_is_NaN ? 2'b11 : (overflow ? 2'b1 : (underflow ? 2'b10 : 2'b0));

    // Sign bit
    assign op3_sign = NaN_input ? 1'b0 : ((inf_x_0) ? 1'b1 : ((op1_sign) ^ (op2_sign)));
    // Exponent
    assign op3_exp = (out_is_NaN | out_is_inf) ? 8'b11111111 : ((out_is_zero | exp_underflow_border) ? 8'b0 : exp_sum_norm);
    // Fraction
    assign op3_frac = out_is_NaN ? {1'b1, 6'b0} : ((out_is_inf | out_is_zero) ? 7'b0 : ((exp_underflow_border) ? frac_prod_underflow_border : frac_prod_norm));

endmodule

src_iverilog/iv_fp_mul_tb.v
`timescale 1 ns / 100 ps
module iv_fp_mul_tb;
    parameter ERROR_WIDTH = 2;
    parameter DATA_WIDTH = 16;  // Set according to your module's requirement
    reg [DATA_WIDTH-1:0] in1, in2;
    wire [DATA_WIDTH-1:0] out;
    wire [ERROR_WIDTH-1:0] error;

    // Instantiate the module
    iv_fp_mul uut (
        .in1(in1),
        .in2(in2),
        .out(out),
        .error(error)
    );

    // Memory to store input test vectors
    reg [DATA_WIDTH-1:0] num_1 [0:9]; // Adjust size based on the number of test cases
    reg [DATA_WIDTH-1:0] num_2 [0:9]; // Adjust size based on the number of test cases
    integer i;

    initial begin
        // $readmemh("../../../gen_tb/test_files/EDGE_A.txt", num_1);
        // $readmemh("../../../gen_tb/test_files/EDGE_B.txt", num_2);
        $readmemh("../../../gen_tb/test_files/INPUT_A.txt", num_1);
        $readmemh("../../../gen_tb/test_files/INPUT_B.txt", num_2);
        
        // Apply test vectors
        for (i = 0; i < 10; i++) begin  // Loop through all test cases
            in1 = num_1[i];
            in2 = num_2[i];
            #10; // Delay for observation, adjust as needed

            // Display results for each test
            $display("Test %d: in1 = 0x%h, in2 = 0x%h, out = 0x%h, error = %d", i, in1, in2, out, error);
        end

        $finish; // End simulation
    end

    initial begin
        $dumpfile("iv_fp_mul_tb.vcd");
        $dumpvars(0, iv_fp_mul_tb);
    end

    
endmodule

src_iverilog/iv_fp_mul_tb.vcd
$date
	Wed Jun 12 19:31:12 2024
$end
$version
	Icarus Verilog
$end
$timescale
	100ps
$end
$scope module iv_fp_mul_tb $end
$var wire 16 ! out [15:0] $end
$var wire 2 " error [1:0] $end
$var parameter 32 # DATA_WIDTH $end
$var parameter 32 $ ERROR_WIDTH $end
$var reg 16 % in1 [15:0] $end
$var reg 16 & in2 [15:0] $end
$var integer 32 ' i [31:0] $end
$scope module uut $end
$var wire 1 ( NaN_input $end
$var wire 1 ) exp_underflow_border $end
$var wire 16 * in1 [15:0] $end
$var wire 16 + in2 [15:0] $end
$var wire 1 , inf_x_0 $end
$var wire 1 - out_is_NaN $end
$var wire 1 . out_is_inf $end
$var wire 1 / out_is_zero $end
$var wire 1 0 overflow $end
$var wire 1 1 underflow $end
$var wire 16 2 out [15:0] $end
$var wire 1 3 op3_sign $end
$var wire 7 4 op3_frac [6:0] $end
$var wire 8 5 op3_exp [7:0] $end
$var wire 1 6 op2_sign $end
$var wire 7 7 op2_frac [6:0] $end
$var wire 8 8 op2_exp [7:0] $end
$var wire 1 9 op1_sign $end
$var wire 7 : op1_frac [6:0] $end
$var wire 8 ; op1_exp [7:0] $end
$var wire 1 < normalise $end
$var wire 1 = in2_is_zero $end
$var wire 1 > in2_is_inf $end
$var wire 1 ? in2_is_NaN $end
$var wire 1 @ in1_is_zero $end
$var wire 1 A in1_is_inf $end
$var wire 1 B in1_is_NaN $end
$var wire 7 C frac_prod_underflow_border [6:0] $end
$var wire 7 D frac_prod_norm [6:0] $end
$var wire 16 E frac_prod [15:0] $end
$var wire 9 F exp_sum_plus_1 [8:0] $end
$var wire 8 G exp_sum_norm [7:0] $end
$var wire 9 H exp_sum_exp1_plus_exp2 [8:0] $end
$var wire 9 I exp_sum [8:0] $end
$var wire 2 J error [1:0] $end
$var parameter 32 K DATA_WIDTH $end
$var parameter 32 L ERROR_WIDTH $end
$var parameter 32 M EXP_WIDTH $end
$var parameter 32 N FRAC_WIDTH $end
$scope module is_NaN_1 $end
$var wire 1 B is_NaN_out $end
$var wire 16 O num [15:0] $end
$var wire 7 P frac [6:0] $end
$var wire 8 Q exp [7:0] $end
$var parameter 32 R DATA_WIDTH $end
$var parameter 32 S EXP_WIDTH $end
$var parameter 32 T FRAC_WIDTH $end
$upscope $end
$scope module is_NaN_2 $end
$var wire 1 ? is_NaN_out $end
$var wire 16 U num [15:0] $end
$var wire 7 V frac [6:0] $end
$var wire 8 W exp [7:0] $end
$var parameter 32 X DATA_WIDTH $end
$var parameter 32 Y EXP_WIDTH $end
$var parameter 32 Z FRAC_WIDTH $end
$upscope $end
$scope module is_inf_1 $end
$var wire 1 A is_inf_out $end
$var wire 16 [ num [15:0] $end
$var wire 7 \ frac [6:0] $end
$var wire 8 ] exp [7:0] $end
$var parameter 32 ^ DATA_WIDTH $end
$var parameter 32 _ EXP_WIDTH $end
$var parameter 32 ` FRAC_WIDTH $end
$upscope $end
$scope module is_inf_2 $end
$var wire 1 > is_inf_out $end
$var wire 16 a num [15:0] $end
$var wire 7 b frac [6:0] $end
$var wire 8 c exp [7:0] $end
$var parameter 32 d DATA_WIDTH $end
$var parameter 32 e EXP_WIDTH $end
$var parameter 32 f FRAC_WIDTH $end
$upscope $end
$scope module is_zero_1 $end
$var wire 1 @ is_zero_out $end
$var wire 16 g num [15:0] $end
$var wire 7 h frac [6:0] $end
$var wire 8 i exp [7:0] $end
$var parameter 32 j DATA_WIDTH $end
$var parameter 32 k EXP_WIDTH $end
$var parameter 32 l FRAC_WIDTH $end
$upscope $end
$scope module is_zero_2 $end
$var wire 1 = is_zero_out $end
$var wire 16 m num [15:0] $end
$var wire 7 n frac [6:0] $end
$var wire 8 o exp [7:0] $end
$var parameter 32 p DATA_WIDTH $end
$var parameter 32 q EXP_WIDTH $end
$var parameter 32 r FRAC_WIDTH $end
$upscope $end
$upscope $end
$upscope $end
$enddefinitions $end
$comment Show the parameter values. $end
$dumpall
b111 r
b1000 q
b10000 p
b111 l
b1000 k
b10000 j
b111 f
b1000 e
b10000 d
b111 `
b1000 _
b10000 ^
b111 Z
b1000 Y
b10000 X
b111 T
b1000 S
b10000 R
b111 N
b1000 M
b10 L
b10000 K
b10 $
b10000 #
$end
#0
$dumpvars
b0 o
b1 n
b1 m
b0 i
b1 h
b1 g
b0 c
b1 b
b1 a
b0 ]
b1 \
b1 [
b0 W
b1 V
b1 U
b0 Q
b1 P
b1 O
b10 J
b110000001 I
b0 H
b10000001 G
b110000010 F
b100000100000001 E
b10 D
b100000 C
0B
0A
0@
0?
0>
0=
0<
b0 ;
b1 :
09
b0 8
b1 7
06
b0 5
b0 4
03
b0 2
11
00
1/
0.
0-
0,
b1 +
b1 *
0)
0(
b0 '
b1 &
b1 %
b10 "
b0 !
$end
#100
0/
b11111111 5
01
b11 "
b11 J
b111111111000000 !
b111111111000000 2
b1000000 4
1.
1-
10
b10000000 G
b1111110 D
1(
1?
1<
b1111111 C
1B
b11111111 8
b1111111 7
b11111111 W
b1111111 V
b11111111 c
b1111111 b
b11111111 o
b1111111 n
b110000000 F
b101111111 I
b111111110 H
b11111111 ;
b1111111000000001 E
b1111111 :
b11111111 Q
b1111111 P
b11111111 ]
b1111111 \
b11111111 i
b1111111 h
b111111111111111 &
b111111111111111 +
b111111111111111 U
b111111111111111 a
b111111111111111 m
b111111111111111 %
b111111111111111 *
b111111111111111 O
b111111111111111 [
b111111111111111 g
b1 '
#200
b10000001 5
0.
b0 "
b0 J
b100000010000010 !
b100000010000010 2
b10 4
00
0-
b10000001 G
b10 D
0(
0<
0?
b100000 C
0B
b10000000 8
b1 7
b10000000 W
b1 V
b10000000 c
b1 b
b10000000 o
b1 n
b10000010 F
b10000001 I
b100000000 H
b10000000 ;
b100000100000001 E
b1 :
b10000000 Q
b1 P
b10000000 ]
b1 \
b10000000 i
b1 h
b100000000000001 &
b100000000000001 +
b100000000000001 U
b100000000000001 a
b100000000000001 m
b100000000000001 %
b100000000000001 *
b100000000000001 O
b100000000000001 [
b100000000000001 g
b10 '
#300
b0 "
b0 J
b100000 4
0/
b100000 !
b100000 2
b0 5
01
1)
b11111111 G
b111111 8
b111111 W
b111111 c
b111111 o
b0 F
b111111111 I
b1111110 H
b111111 ;
b111111 Q
b111111 ]
b111111 i
b1111110000001 &
b1111110000001 +
b1111110000001 U
b1111110000001 a
b1111110000001 m
b1111110000001 %
b1111110000001 *
b1111110000001 O
b1111110000001 [
b1111110000001 g
b11 '
#400
b11111111 5
b1 "
b1 J
b111111110000000 !
b111111110000000 2
b0 4
1.
0)
10
b1111110 G
b1111110 D
1<
b1111111 C
b11111110 8
b1111111 7
b11111110 W
b1111111 V
b11111110 c
b1111111 b
b11111110 o
b1111111 n
b101111110 F
b101111101 I
b111111100 H
b11111110 ;
b1111111000000001 E
b1111111 :
b11111110 Q
b1111111 P
b11111110 ]
b1111111 \
b11111110 i
b1111111 h
b111111101111111 &
b111111101111111 +
b111111101111111 U
b111111101111111 a
b111111101111111 m
b111111101111111 %
b111111101111111 *
b111111101111111 O
b111111101111111 [
b111111101111111 g
b100 '
#500
b100001 4
b100001 !
b100001 2
b0 5
0/
b0 "
b0 J
01
0.
1)
00
b11111111 G
b100 D
0<
b100001 C
b111111 8
b10 7
b111111 W
b10 V
b111111 c
b10 b
b111111 o
b10 n
b0 F
b111111111 I
b1111110 H
b111111 ;
b100001000000100 E
b10 :
b111111 Q
b10 P
b111111 ]
b10 \
b111111 i
b10 h
b1111110000010 &
b1111110000010 +
b1111110000010 U
b1111110000010 a
b1111110000010 m
b1111110000010 %
b1111110000010 *
b1111110000010 O
b1111110000010 [
b1111110000010 g
b101 '
#600
b1111111 !
b1111111 2
b1111111 4
b0 G
b1111110 D
1<
b1111111 C
b1111111 7
b1111111 V
b1111111 b
b1111111 n
b1111111000000001 E
b1111111 :
b1111111 P
b1111111 \
b1111111 h
b1111111111111 &
b1111111111111 +
b1111111111111 U
b1111111111111 a
b1111111111111 m
b1111111111111 %
b1111111111111 *
b1111111111111 O
b1111111111111 [
b1111111111111 g
b110 '
#700
b1 5
0)
b10000000 !
b10000000 2
b0 4
b1 G
b0 D
0<
b100000 C
b1000000 8
b0 7
b1000000 W
b0 V
b1000000 c
b0 b
b1000000 o
b0 n
b10 F
b1 I
b10000000 H
b1000000 ;
b100000000000000 E
b0 :
b1000000 Q
b0 P
b1000000 ]
b0 \
b1000000 i
b0 h
b10000000000000 &
b10000000000000 +
b10000000000000 U
b10000000000000 a
b10000000000000 m
b10000000000000 %
b10000000000000 *
b10000000000000 O
b10000000000000 [
b10000000000000 g
b111 '
#800
b1011 4
b11101000001011 !
b11101000001011 2
b1110100 5
b1110100 G
b1011 D
1<
b1000101 C
b1110101 8
b10000 7
b1110101 W
b10000 V
b1110101 c
b10000 b
b1110101 o
b10000 n
b1110100 F
b1110011 I
b11110010 H
b1111101 ;
b1000101110000000 E
b1111000 :
b1111101 Q
b1111000 P
b1111101 ]
b1111000 \
b1111101 i
b1111000 h
b11101010010000 &
b11101010010000 +
b11101010010000 U
b11101010010000 a
b11101010010000 m
b11111011111000 %
b11111011111000 *
b11111011111000 O
b11111011111000 [
b11111011111000 g
b1000 '
#900
b1011101 4
b11111011011101 !
b11111011011101 2
b1111101 5
b1111101 G
b1011101 D
0<
b110111 C
b1111110 8
b100000 7
b1111110 W
b100000 V
b1111110 c
b100000 b
b1111110 o
b100000 n
b1111110 F
b1111101 I
b11111100 H
b1111110 ;
b110111010100000 E
b110001 :
b1111110 Q
b110001 P
b1111110 ]
b110001 \
b1111110 i
b110001 h
b11111100100000 &
b11111100100000 +
b11111100100000 U
b11111100100000 a
b11111100100000 m
b11111100110001 %
b11111100110001 *
b11111100110001 O
b11111100110001 [
b11111100110001 g
b1001 '
#1000
b1010 '
