src_iverilog/is_zero.v
module is_zero (num, is_zero_out);
    parameter DATA_WIDTH = 16;
    parameter EXP_WIDTH = 8;
    parameter FRAC_WIDTH = 7;

    input [DATA_WIDTH-1:0] num;
    output is_zero_out;

    wire [EXP_WIDTH-1:0] exp;
    wire [FRAC_WIDTH-1:0] frac;

    assign exp = num[DATA_WIDTH-2:DATA_WIDTH-1-EXP_WIDTH];
    assign frac = num[FRAC_WIDTH-1:0];

    assign is_zero_out = ~((|exp) | (|frac));
endmodule

src_iverilog/is_inf.v
module is_inf (num, is_inf_out);
    parameter DATA_WIDTH = 16;
    parameter EXP_WIDTH = 8;
    parameter FRAC_WIDTH = 7;

    input [DATA_WIDTH-1:0] num;
    output is_inf_out;

    wire [EXP_WIDTH-1:0] exp;
    wire [FRAC_WIDTH-1:0] frac;

    assign exp = num[DATA_WIDTH-2:DATA_WIDTH-1-EXP_WIDTH];
    assign frac = num[FRAC_WIDTH-1:0];

    assign is_inf_out = (&exp) & ~(|frac);
endmodule

src_iverilog/is_NaN.v
module is_NaN (num, is_NaN_out);
    parameter DATA_WIDTH = 16;
    parameter EXP_WIDTH = 8;
    parameter FRAC_WIDTH = 7;

    input [DATA_WIDTH-1:0] num;
    output is_NaN_out;

    wire [EXP_WIDTH-1:0] exp;
    wire [FRAC_WIDTH-1:0] frac;

    assign exp = num[DATA_WIDTH-2:DATA_WIDTH-1-EXP_WIDTH];
    assign frac = num[FRAC_WIDTH-1:0];

    assign is_NaN_out = (&exp) & (|frac);
endmodule

src_iverilog/iv_fp_mul.v

module iv_fp_mul(
    input [DATA_WIDTH-1:0] in1,
    input [DATA_WIDTH-1:0] in2,
    output [DATA_WIDTH-1:0] out,
    output [ERROR_WIDTH-1:0] error
);
    parameter DATA_WIDTH = 16;
    parameter EXP_WIDTH = 8;
    parameter FRAC_WIDTH = 7;
    parameter ERROR_WIDTH = 2;

    wire op1_sign, op2_sign, op3_sign;
    wire [EXP_WIDTH-1:0] op1_exp, op2_exp, op3_exp;
    wire [FRAC_WIDTH-1:0] op1_frac, op2_frac, op3_frac;

    assign op1_sign = in1[DATA_WIDTH-1];
    assign op2_sign = in2[DATA_WIDTH-1];

    assign op1_exp = in1[DATA_WIDTH-2:DATA_WIDTH-1-EXP_WIDTH];
    assign op2_exp = in2[DATA_WIDTH-2:DATA_WIDTH-1-EXP_WIDTH];

    assign op1_frac = in1[FRAC_WIDTH-1:0];
    assign op2_frac = in2[FRAC_WIDTH-1:0];

    assign out = {op3_sign, op3_exp, op3_frac};

    // Input / Output Setup Complete

    // Fraction / Mantissa
    wire [(2*FRAC_WIDTH)+1:0] frac_prod;
    wire normalise;
    wire [FRAC_WIDTH-1:0] frac_prod_norm;
    assign frac_prod = {1'b1, op1_frac} * {1'b1, op2_frac};
    assign normalise = frac_prod[(2*FRAC_WIDTH)+1];
    assign frac_prod_norm = normalise ? frac_prod[(2*FRAC_WIDTH):FRAC_WIDTH+1] : frac_prod[(2*FRAC_WIDTH)-1:FRAC_WIDTH];
    
    // Exponent
    wire [EXP_WIDTH:0] exp_sum, exp_sum_plus_1, exp_sum_exp1_plus_exp2;
    wire [EXP_WIDTH-1:0] exp_sum_norm;
    assign exp_sum_exp1_plus_exp2 = {1'b0, op1_exp} + {1'b0, op2_exp};
    assign exp_sum = exp_sum_exp1_plus_exp2 - 9'd127; // 9 is exp_sum width
    assign exp_sum_plus_1 = exp_sum + 9'b1; // 9 is exp_sum width
    assign exp_sum_norm = normalise ? exp_sum_plus_1[EXP_WIDTH-1:0] : exp_sum[EXP_WIDTH-1:0];

    // Error detection
    wire in1_is_NaN, in1_is_inf, in1_is_zero;
    wire in2_is_NaN, in2_is_inf, in2_is_zero;
    wire out_is_NaN, out_is_inf, out_is_zero;

    wire overflow, underflow, NaN, inf;
    assign overflow = exp_sum_exp1_plus_exp2[EXP_WIDTH] & (normalise ? exp_sum_plus_1[EXP_WIDTH] : exp_sum[EXP_WIDTH]);

    assign underflow = ~(exp_sum_exp1_plus_exp2[EXP_WIDTH]) & (normalise ? exp_sum_plus_1[EXP_WIDTH] : exp_sum[EXP_WIDTH]);

    is_NaN is_NaN_1(.num(in1), .is_NaN_out(in1_is_NaN));
    is_inf is_inf_1(.num(in1), .is_inf_out(in1_is_inf));
    is_zero is_zero_1(.num(in1), .is_zero_out(in1_is_zero));

    is_NaN is_NaN_2(.num(in2), .is_NaN_out(in2_is_NaN));
    is_inf is_inf_2(.num(in2), .is_inf_out(in2_is_inf));
    is_zero is_zero_2(.num(in2), .is_zero_out(in2_is_zero));


    assign out_is_NaN = (in1_is_NaN) | (in2_is_NaN) | ((in1_is_inf) & (in2_is_zero)) | ((in1_is_zero) & (in2_is_inf));
    assign out_is_inf = ((in1_is_inf) & ~(in2_is_zero) & ~(in2_is_NaN)) | (~(in1_is_zero) & ~(in1_is_NaN) & (in2_is_inf));
    assign out_is_zero = (~(in1_is_inf) & ~(in1_is_NaN) & (in2_is_zero)) | (~(in1_is_zero) & ~(in2_is_NaN) & ~(in2_is_inf));
    
    assign error = out_is_NaN ? 2'b11 : (overflow ? 2'b1 : (underflow ? 2'b10 : 2'b0));

    // Sign bit
    assign op3_sign = (op1_sign) ^ (op2_sign); // Might need to change
    // Exponent
    assign op3_exp = (out_is_NaN | out_is_inf) ? 8'b11111111 : ((out_is_zero | underflow) ? 8'b0 : exp_sum_norm);
    // Fraction
    assign op3_frac = out_is_NaN ? {1'b1, 6'b0} : ((out_is_inf | out_is_zero | underflow) ? 7'b0 : frac_prod_norm);

endmodule

src_iverilog/iv_fp_mul_tb.v
`timescale 1 ns / 100 ps
module iv_fp_mul_tb;
    parameter ERROR_WIDTH = 2;
    parameter DATA_WIDTH = 16;  // Set according to your module's requirement
    reg [DATA_WIDTH-1:0] in1, in2;
    wire [DATA_WIDTH-1:0] out;
    wire [ERROR_WIDTH-1:0] error;

    // Instantiate the module
    iv_fp_mul uut (
        .in1(in1),
        .in2(in2),
        .out(out),
        .error(error)
    );

    // Memory to store input test vectors
    reg [DATA_WIDTH-1:0] num_1 [0:9]; // Adjust size based on the number of test cases
    reg [DATA_WIDTH-1:0] num_2 [0:9]; // Adjust size based on the number of test cases
    integer i;

    initial begin
        // $readmemh("../../../gen_tb/test_files/EDGE_A.txt", num_1);
        // $readmemh("../../../gen_tb/test_files/EDGE_B.txt", num_2);
        $readmemh("../../../gen_tb/test_files/INPUT_A.txt", num_1);
        $readmemh("../../../gen_tb/test_files/INPUT_B.txt", num_2);
        
        // Apply test vectors
        for (i = 0; i < 10; i++) begin  // Loop through all test cases
            in1 = num_1[i];
            in2 = num_2[i];
            #10; // Delay for observation, adjust as needed

            // Display results for each test
            $display("Test %d: in1 = 0x%h, in2 = 0x%h, out = 0x%h, error = %d", i, in1, in2, out, error);
        end

        $finish; // End simulation
    end

    initial begin
        $dumpfile("iv_fp_mul_tb.vcd");
        $dumpvars(0, iv_fp_mul_tb);
    end

    
endmodule

src_iverilog/iv_fp_mul_tb.vcd
$date
	Wed Jun 05 14:14:46 2024
$end
$version
	Icarus Verilog
$end
$timescale
	100ps
$end
$scope module iv_fp_mul_tb $end
$var wire 16 ! out [15:0] $end
$var wire 2 " error [1:0] $end
$var parameter 32 # DATA_WIDTH $end
$var parameter 32 $ ERROR_WIDTH $end
$var reg 16 % in1 [15:0] $end
$var reg 16 & in2 [15:0] $end
$var integer 32 ' i [31:0] $end
$scope module uut $end
$var wire 16 ( in1 [15:0] $end
$var wire 16 ) in2 [15:0] $end
$var wire 1 * op3_sign $end
$var wire 1 + out_is_NaN $end
$var wire 1 , out_is_inf $end
$var wire 1 - out_is_zero $end
$var wire 1 . overflow $end
$var wire 1 / underflow $end
$var wire 16 0 out [15:0] $end
$var wire 7 1 op3_frac [6:0] $end
$var wire 8 2 op3_exp [7:0] $end
$var wire 1 3 op2_sign $end
$var wire 7 4 op2_frac [6:0] $end
$var wire 8 5 op2_exp [7:0] $end
$var wire 1 6 op1_sign $end
$var wire 7 7 op1_frac [6:0] $end
$var wire 8 8 op1_exp [7:0] $end
$var wire 1 9 normalise $end
$var wire 1 : in2_is_zero $end
$var wire 1 ; in2_is_inf $end
$var wire 1 < in2_is_NaN $end
$var wire 1 = in1_is_zero $end
$var wire 1 > in1_is_inf $end
$var wire 1 ? in1_is_NaN $end
$var wire 7 @ frac_prod_norm [6:0] $end
$var wire 16 A frac_prod [15:0] $end
$var wire 9 B exp_sum_plus_1 [8:0] $end
$var wire 8 C exp_sum_norm [7:0] $end
$var wire 9 D exp_sum_exp1_plus_exp2 [8:0] $end
$var wire 9 E exp_sum [8:0] $end
$var wire 2 F error [1:0] $end
$var parameter 32 G DATA_WIDTH $end
$var parameter 32 H ERROR_WIDTH $end
$var parameter 32 I EXP_WIDTH $end
$var parameter 32 J FRAC_WIDTH $end
$scope module is_NaN_1 $end
$var wire 1 ? is_NaN_out $end
$var wire 16 K num [15:0] $end
$var wire 7 L frac [6:0] $end
$var wire 8 M exp [7:0] $end
$var parameter 32 N DATA_WIDTH $end
$var parameter 32 O EXP_WIDTH $end
$var parameter 32 P FRAC_WIDTH $end
$upscope $end
$scope module is_NaN_2 $end
$var wire 1 < is_NaN_out $end
$var wire 16 Q num [15:0] $end
$var wire 7 R frac [6:0] $end
$var wire 8 S exp [7:0] $end
$var parameter 32 T DATA_WIDTH $end
$var parameter 32 U EXP_WIDTH $end
$var parameter 32 V FRAC_WIDTH $end
$upscope $end
$scope module is_inf_1 $end
$var wire 1 > is_inf_out $end
$var wire 16 W num [15:0] $end
$var wire 7 X frac [6:0] $end
$var wire 8 Y exp [7:0] $end
$var parameter 32 Z DATA_WIDTH $end
$var parameter 32 [ EXP_WIDTH $end
$var parameter 32 \ FRAC_WIDTH $end
$upscope $end
$scope module is_inf_2 $end
$var wire 1 ; is_inf_out $end
$var wire 16 ] num [15:0] $end
$var wire 7 ^ frac [6:0] $end
$var wire 8 _ exp [7:0] $end
$var parameter 32 ` DATA_WIDTH $end
$var parameter 32 a EXP_WIDTH $end
$var parameter 32 b FRAC_WIDTH $end
$upscope $end
$scope module is_zero_1 $end
$var wire 1 = is_zero_out $end
$var wire 16 c num [15:0] $end
$var wire 7 d frac [6:0] $end
$var wire 8 e exp [7:0] $end
$var parameter 32 f DATA_WIDTH $end
$var parameter 32 g EXP_WIDTH $end
$var parameter 32 h FRAC_WIDTH $end
$upscope $end
$scope module is_zero_2 $end
$var wire 1 : is_zero_out $end
$var wire 16 i num [15:0] $end
$var wire 7 j frac [6:0] $end
$var wire 8 k exp [7:0] $end
$var parameter 32 l DATA_WIDTH $end
$var parameter 32 m EXP_WIDTH $end
$var parameter 32 n FRAC_WIDTH $end
$upscope $end
$upscope $end
$upscope $end
$enddefinitions $end
$comment Show the parameter values. $end
$dumpall
b111 n
b1000 m
b10000 l
b111 h
b1000 g
b10000 f
b111 b
b1000 a
b10000 `
b111 \
b1000 [
b10000 Z
b111 V
b1000 U
b10000 T
b111 P
b1000 O
b10000 N
b111 J
b1000 I
b10 H
b10000 G
b10 $
b10000 #
$end
#0
$dumpvars
b0 k
b1 j
b1 i
b0 e
b1 d
b1 c
b0 _
b1 ^
b1 ]
b0 Y
b1 X
b1 W
b0 S
b1 R
b1 Q
b0 M
b1 L
b1 K
b10 F
b110000001 E
b0 D
b10000001 C
b110000010 B
b100000100000001 A
b10 @
0?
0>
0=
0<
0;
0:
09
b0 8
b1 7
06
b0 5
b1 4
03
b0 2
b0 1
b0 0
1/
0.
1-
0,
0+
0*
b1 )
b1 (
b0 '
b1 &
b1 %
b10 "
b0 !
$end
#100
b11111111 2
0-
b111111111000000 !
b111111111000000 0
b1000000 1
b11 "
b11 F
1+
0/
1.
b10000000 C
b1111110 @
1<
19
1?
b11111111 5
b1111111 4
b11111111 S
b1111111 R
b11111111 _
b1111111 ^
b11111111 k
b1111111 j
b110000000 B
b101111111 E
b111111110 D
b11111111 8
b1111111000000001 A
b1111111 7
b11111111 M
b1111111 L
b11111111 Y
b1111111 X
b11111111 e
b1111111 d
b111111111111111 &
b111111111111111 )
b111111111111111 Q
b111111111111111 ]
b111111111111111 i
b111111111111111 %
b111111111111111 (
b111111111111111 K
b111111111111111 W
b111111111111111 c
b1 '
#200
b0 2
1-
b0 "
b0 F
b0 !
b0 0
b0 1
0+
0.
b10000001 C
b10 @
09
0<
0?
b10000000 5
b1 4
b10000000 S
b1 R
b10000000 _
b1 ^
b10000000 k
b1 j
b10000010 B
b10000001 E
b100000000 D
b10000000 8
b100000100000001 A
b1 7
b10000000 M
b1 L
b10000000 Y
b1 X
b10000000 e
b1 d
b100000000000001 &
b100000000000001 )
b100000000000001 Q
b100000000000001 ]
b100000000000001 i
b100000000000001 %
b100000000000001 (
b100000000000001 K
b100000000000001 W
b100000000000001 c
b10 '
#300
b10 "
b10 F
1/
b11111111 C
b111111 5
b111111 S
b111111 _
b111111 k
b0 B
b111111111 E
b1111110 D
b111111 8
b111111 M
b111111 Y
b111111 e
b1111110000001 &
b1111110000001 )
b1111110000001 Q
b1111110000001 ]
b1111110000001 i
b1111110000001 %
b1111110000001 (
b1111110000001 K
b1111110000001 W
b1111110000001 c
b11 '
#400
b0 "
b0 F
0/
b11 C
b1000001 5
b1000001 S
b1000001 _
b1000001 k
b100 B
b11 E
b10000010 D
b1000001 8
b1000001 M
b1000001 Y
b1000001 e
b10000010000001 &
b10000010000001 )
b10000010000001 Q
b10000010000001 ]
b10000010000001 i
b10000010000001 %
b10000010000001 (
b10000010000001 K
b10000010000001 W
b10000010000001 c
b100 '
#500
b1111010 C
b1111000 @
b1111101 5
b1110011 4
b1111101 S
b1110011 R
b1111101 _
b1110011 ^
b1111101 k
b1110011 j
b1111011 B
b1111010 E
b11111001 D
b1111100 8
b111110001011001 A
b11 7
b1111100 M
b11 L
b1111100 Y
b11 X
b1111100 e
b11 d
b11111011110011 &
b11111011110011 )
b11111011110011 Q
b11111011110011 ]
b11111011110011 i
b11111000000011 %
b11111000000011 (
b11111000000011 K
b11111000000011 W
b11111000000011 c
b101 '
#600
b1111110 C
b11010 @
19
b1111110 5
b101100 4
b1111110 S
b101100 R
b1111110 _
b101100 ^
b1111110 k
b101100 j
b1111110 B
b1111101 E
b11111100 D
b1111110 8
b1001101010001000 A
b1100110 7
b1111110 M
b1100110 L
b1111110 Y
b1100110 X
b1111110 e
b1100110 d
b11111100101100 &
b11111100101100 )
b11111100101100 Q
b11111100101100 ]
b11111100101100 i
b11111101100110 %
b11111101100110 (
b11111101100110 K
b11111101100110 W
b11111101100110 c
b110 '
#700
b1111101 C
b1011010 @
09
b11001 4
b11001 R
b11001 ^
b11001 j
b110110101011111 A
b110111 7
b110111 L
b110111 X
b110111 d
b11111100011001 &
b11111100011001 )
b11111100011001 Q
b11111100011001 ]
b11111100011001 i
b11111100110111 %
b11111100110111 (
b11111100110111 K
b11111100110111 W
b11111100110111 c
b111 '
#800
b1110100 C
b1011 @
19
b1110101 5
b10000 4
b1110101 S
b10000 R
b1110101 _
b10000 ^
b1110101 k
b10000 j
b1110100 B
b1110011 E
b11110010 D
b1111101 8
b1000101110000000 A
b1111000 7
b1111101 M
b1111000 L
b1111101 Y
b1111000 X
b1111101 e
b1111000 d
b11101010010000 &
b11101010010000 )
b11101010010000 Q
b11101010010000 ]
b11101010010000 i
b11111011111000 %
b11111011111000 (
b11111011111000 K
b11111011111000 W
b11111011111000 c
b1000 '
#900
b1111101 C
b1011101 @
09
b1111110 5
b100000 4
b1111110 S
b100000 R
b1111110 _
b100000 ^
b1111110 k
b100000 j
b1111110 B
b1111101 E
b11111100 D
b1111110 8
b110111010100000 A
b110001 7
b1111110 M
b110001 L
b1111110 Y
b110001 X
b1111110 e
b110001 d
b11111100100000 &
b11111100100000 )
b11111100100000 Q
b11111100100000 ]
b11111100100000 i
b11111100110001 %
b11111100110001 (
b11111100110001 K
b11111100110001 W
b11111100110001 c
b1001 '
#1000
b1010 '
